iflow_mcp_sketchup_mcp-0.1.18.dist-info/licenses/LICENSE
sketchup_mcp/__init__.py
sketchup_mcp/__main__.py
sketchup_mcp/server.py
iflow_mcp_sketchup_mcp-0.1.18.dist-info/METADATA
iflow_mcp_sketchup_mcp-0.1.18.dist-info/WHEEL
iflow_mcp_sketchup_mcp-0.1.18.dist-info/entry_points.txt
iflow_mcp_sketchup_mcp-0.1.18.dist-info/top_level.txt
iflow_mcp_sketchup_mcp-0.1.18.dist-info/RECORD
