Metadata-Version: 2.4
Name: iflow-mcp_sketchup-mcp
Version: 0.1.18
Summary: Sketchup integration through Model Context Protocol
Author-email: Your Name <your.email@example.com>
License: MIT
Project-URL: Homepage, https://github.com/yourusername/sketchup-mcp
Project-URL: Issues, https://github.com/yourusername/sketchup-mcp/issues
Classifier: Programming Language :: Python :: 3
Classifier: License :: OSI Approved :: MIT License
Classifier: Operating System :: OS Independent
Requires-Python: >=3.10
License-File: LICENSE
Requires-Dist: mcp[cli]>=1.3.0
Dynamic: license-file
